{
  "name": "Damol Ark",
  "description": "a usable ITEM that if own HERO is RANGED or HYBRID a DISARM spell will be added to HERO",
  "type": "USABLE_ITEM",
  "spells": [
    {
      "spellId": "da_add_disarm",
      "type": "CARD_EFFECT",
      "definiteType": "ADD_SPELL",
      "availabilityType": "ON_START",
      "target": {
        "owner": {
          "own": true
        },
        "cardType": {
          "hero": true
        },
        "attackType": {
          "ranged": true,
          "hybrid": true
        },
        "isForDeckCards": true
      },
      "carryingSpell": {
        "spellId": "da_disarm",
        "type": "BUFF",
        "definiteType": "DISARM_BUFF",
        "availabilityType": "ON_ATTACK",
        "target": {
          "dimensions": {
            "row": 1,
            "column": 1
          },
          "owner": {
            "enemy": true
          },
          "cardType": {
            "hero": true,
            "minion": true
          },
          "attackType": {
            "melee": true,
            "ranged": true,
            "hybrid": true
          }
        },
        "duration": 1
      }
    }
  ],
  "price": 30000
}