{
  "name": "Bahman",
  "description": "a melee MINION with 9 AP, 16 HP, and ON_SPAWN decreases HP of a random enemy MINION 16 units",
  "type": "MINION",
  "spells": [
    {
      "spellId": "b_random_hit",
      "type": "CARD_EFFECT",
      "definiteType": "DECREASE_HP_CARD_EFFECT",
      "availabilityType": "ON_PUT",
      "target": {
        "isRandom": true,
        "dimensions": {
          "row": 10,
          "column": 18
        },
        "owner": {
          "enemy": true
        },
        "cardType": {
          "minion": true
        },
        "attackType": {
          "melee": true,
          "ranged": true,
          "hybrid": true
        }
      },
      "numberOfChange": 16
    }
  ],
  "defaultAp": 9,
  "defaultHp": 16,
  "mannaPoint": 8,
  "price": 450,
  "attackType": "MELEE"
}